{
  "type": "vortex:calcite_pillar_structure",
  "config": {
    "features": [
      {
        "feature": {
          "type": "vortex:structure_feature",
          "config": {
            "structure": "vortex:calcite_pillar0",
            "random_rotation": true,
            "random_mirror": true,
            "ignored_blocks": "minecraft:air"
          }
        },
        "placement": []
      },
      {
        "feature": {
          "type": "vortex:structure_feature",
          "config": {
            "structure": "vortex:calcite_pillar1",
            "random_rotation": true,
            "random_mirror": true,
            "ignored_blocks": "minecraft:air"
          }
        },
        "placement": []
      }
    ]
  }
}